rllib/__init__.py
rllib-0.0.1.dist-info/LICENSE
rllib-0.0.1.dist-info/METADATA
rllib-0.0.1.dist-info/WHEEL
rllib-0.0.1.dist-info/top_level.txt
rllib-0.0.1.dist-info/RECORD
