Metadata-Version: 1.0
Name: rllib
Version: 0.0.1
Summary: A lib for RL
Home-page: https://github.com/zhangdongkun98/rl-lib
Author: Zhang Dongkun
Author-email: zhangdongkun98@gmail.com
License: UNKNOWN
Platform: UNKNOWN
